[
    {
      "$schema": "https://developer.microsoft.com/en-us/json-schemas/pnp/samples/v1.0/metadata-schema.json",
      "name": "pnp-powerplatform-snippets-progressbar-gallery",
      "version": "1.0.0.0",
      "source": "pnp",
      "creationDateTime": "2024-12-02T00:00:00.000Z",
      "updateDateTime": "2024-12-02T00:00:00.000Z",
      "title": "Progress Bar Gallery",
      "shortDescription": "This is a snippet that creates a progress bar for a canvas app as component.",
      "longDescription": [
        "This is a snippet that creates a progress bar for a canvas app as component. In the progress bar some icons indicates specific information on a specific step. It is a gallery in which some logic is added on displaying progress steps."
      ],
      "url": "https://github.com/pnp/powerplatform-snippets/tree/main/power-apps/progressbar-gallery/",
      "products": [
        "Power Platform",
        "Power Apps",
        "powerplatform-snippets",
        "power-apps-snippets"
      ],
      "tags": [],
      "categories": [],
      "metadata": [
        {
          "key": "Product",
          "value": "Power Apps"
        },
        {
          "key": "Type",
          "value": "Snippet"
        }
      ],
      "thumbnails": [
        {
          "type": "image",
          "order": 100,
          "url": "https://raw.githubusercontent.com/pnp/powerplatform-snippets/refs/heads/main/power-apps/progressbar-gallery/assets/progressbar.png",
          "alt": "Preview PNG"
        }
      ],
      "authors": [
        {
          "gitHubAccount": "Dutchy365",
          "name": "Elianne Burgers",
          "pictureUrl": "https://github.com/Dutchy365.png"
        }
      ]
    }
  ]
